mysqlquerys/__init__.py
mysqlquerys/connect.py
mysqlquerys/control.py
mysqlquerys/gui.py
mysqlquerys/mysql_rm.py
mysqlquerys/postgresql_rm.py
mysqlquerys/gui/filterWindow.ui
mysqlquerys/gui/gui.ui
mysqlquerys/gui/postgresql_gui.ui
mysqlquerys/sql/aeroclub.sql
mysqlquerys/sql/alimentari.sql
mysqlquerys/sql/apartament.sql
mysqlquerys/sql/asigurari.sql
mysqlquerys/sql/banca.sql
mysqlquerys/sql/expenses.sql
mysqlquerys/sql/income.sql
mysqlquerys/sql/intercontotrans.sql
mysqlquerys/sql/one_time_transactions.sql
mysqlquerys/sql/stat.sql
mysqlquerys-0.2.13.dist-info/METADATA
mysqlquerys-0.2.13.dist-info/WHEEL
mysqlquerys-0.2.13.dist-info/top_level.txt
mysqlquerys-0.2.13.dist-info/RECORD
